cross_section/__init__.py
cross_section/sections.py
cross_section-0.0.1.dev1.dist-info/WHEEL
cross_section-0.0.1.dev1.dist-info/METADATA
cross_section-0.0.1.dev1.dist-info/RECORD
