Metadata-Version: 2.1
Name: cross_section
Version: 0.0.1.dev1
Summary: Analyze structural cross-sections.
Author: Patrick Simon
Author-email: mail@patricksimon.info
Classifier: License :: OSI Approved :: MIT License
